wordcountpy/__init__.py
wordcountpy/plotting.py
wordcountpy/wordcountpy.py
wordcountpy-0.1.0.dist-info/LICENSE
wordcountpy-0.1.0.dist-info/METADATA
wordcountpy-0.1.0.dist-info/WHEEL
wordcountpy-0.1.0.dist-info/RECORD
